winpnp/__init__.py
winpnp/_setupapi.py
winpnp/info/__init__.py
winpnp/info/_pnp_property_mapping.py
winpnp/info/device.py
winpnp/info/setup_class.py
winpnp/properties/__init__.py
winpnp/properties/decoding.py
winpnp/properties/kinds.py
winpnp/properties/pnp_property.py
winpnp/properties/keys/__init__.py
winpnp/properties/keys/bluetooth.py
winpnp/properties/keys/dev_query.py
winpnp/properties/keys/device.py
winpnp/properties/keys/device_class.py
winpnp/properties/keys/device_container.py
winpnp/properties/keys/device_interface.py
winpnp/properties/keys/device_interface_class.py
winpnp/properties/keys/driver_package.py
winpnp-0.0.2.dist-info/METADATA
winpnp-0.0.2.dist-info/WHEEL
winpnp-0.0.2.dist-info/licenses/LICENSE
winpnp-0.0.2.dist-info/RECORD
