Metadata-Version: 2.4
Name: winpnp
Version: 0.0.2
Summary: A package for interacting with Windows Plug and Play (PnP) entities
Project-URL: Homepage, https://github.com/SuperPudding98/winpnp
Project-URL: Issues, https://github.com/SuperPudding98/winpnp/issues
Author-email: Supper Pudding <31290828+SuperPudding98@users.noreply.github.com>
License-Expression: MIT
License-File: LICENSE
Keywords: Windows device,device manager,pnp,setupapi,setupdi
Classifier: Environment :: Win32 (MS Windows)
Classifier: Operating System :: Microsoft :: Windows
Classifier: Programming Language :: Python :: 3
Classifier: Topic :: System :: Hardware
Classifier: Typing :: Typed
Requires-Python: >=3.9
Requires-Dist: more-itertools<11,>=10.2.0
Requires-Dist: pywin32>=306
Provides-Extra: deploy
Requires-Dist: build<2,>=1.2.2; extra == 'deploy'
Requires-Dist: twine<7,>=6.1.0; extra == 'deploy'
Provides-Extra: dev
Requires-Dist: pytest-cases<4,>=3.8.6; extra == 'dev'
Requires-Dist: pytest<9,>=8.2.1; extra == 'dev'
